README.md
setup.py
jetorm/__init__.py
jetorm/jetorm.py
jetorm/utils.py
jetorm.egg-info/PKG-INFO
jetorm.egg-info/SOURCES.txt
jetorm.egg-info/dependency_links.txt
jetorm.egg-info/requires.txt
jetorm.egg-info/top_level.txt