Metadata-Version: 2.1
Name: jetorm
Version: 0.4.7
Summary: JetORM is the simplest ORM of its kind.
Home-page: https://github.com/immadev2k21/JetORM
Author: kapitanov
Author-email: <leonidmilk2007@gmail.com>
License: MIT license
Keywords: db database orm ORM jet JetORM jetorm easy simple
Platform: UNKNOWN
